aws_adfs_login/__init__.py
aws_adfs_login-1.0.3.dist-info/LICENSE
aws_adfs_login-1.0.3.dist-info/METADATA
aws_adfs_login-1.0.3.dist-info/WHEEL
aws_adfs_login-1.0.3.dist-info/top_level.txt
aws_adfs_login-1.0.3.dist-info/RECORD
