Metadata-Version: 2.1
Name: aws-adfs-login
Version: 1.0.3
Summary: Python 3.6+ library to enable ADFS auth against AWS
Home-page: https://github.com/david-poirier-csn/aws_adfs_login
Author: David Poirier
Author-email: david-poirier-csn@users.noreply.github.com
License: UNKNOWN
Keywords: adfs
Platform: UNKNOWN
Classifier: Programming Language :: Python :: 3
Classifier: License :: OSI Approved :: Apache Software License
Classifier: Operating System :: MacOS :: MacOS X
Classifier: Operating System :: POSIX :: Linux
Requires-Python: >= 3.6
Requires-Dist: beautifulsoup4
Requires-Dist: boto3
Requires-Dist: requests
Requires-Dist: requests-ntlm
